peck/__init__.py
peck/a_strategy.py
peck/ab_entry.py
peck/collection.py
peck/commands.py
peck/config_parser.py
peck/entry_writer.py
peck/entrybox.py
peck/errors.py
peck/file_handle.py
peck/first_entry.py
peck/full_entry.py
peck/info_and_paths.py
peck/modify_strats.py
peck/peck.py
peck/second_entry.py
peck/tag_entry.py
peck/title_entry.py
peck/view_strats.py
peck-2.4.4.dist-info/LICENSE.txt
peck-2.4.4.dist-info/METADATA
peck-2.4.4.dist-info/WHEEL
peck-2.4.4.dist-info/entry_points.txt
peck-2.4.4.dist-info/top_level.txt
peck-2.4.4.dist-info/RECORD
