Metadata-Version: 2.1
Name: peck
Version: 2.4.4
Summary: simple notes on the command line
Home-page: https://github.com/jgbarsness/peck
Author: Joseph Barsness
License: MIT
Platform: UNKNOWN
Requires-Python: >=3.7
License-File: LICENSE.txt
